odoo/addons/sale_customer_rank/README.rst
odoo/addons/sale_customer_rank/__init__.py
odoo/addons/sale_customer_rank/__manifest__.py
odoo/addons/sale_customer_rank/i18n/es.po
odoo/addons/sale_customer_rank/i18n/fr.po
odoo/addons/sale_customer_rank/i18n/it.po
odoo/addons/sale_customer_rank/i18n/sale_customer_rank.pot
odoo/addons/sale_customer_rank/models/__init__.py
odoo/addons/sale_customer_rank/models/sale_order.py
odoo/addons/sale_customer_rank/readme/CONTRIBUTORS.md
odoo/addons/sale_customer_rank/readme/DESCRIPTION.md
odoo/addons/sale_customer_rank/static/description/icon.png
odoo/addons/sale_customer_rank/static/description/index.html
odoo/addons/sale_customer_rank/tests/__init__.py
odoo/addons/sale_customer_rank/tests/test_sale_customer_rank.py
odoo_addon_sale_customer_rank-18.0.1.0.0.2.dist-info/METADATA
odoo_addon_sale_customer_rank-18.0.1.0.0.2.dist-info/WHEEL
odoo_addon_sale_customer_rank-18.0.1.0.0.2.dist-info/top_level.txt
odoo_addon_sale_customer_rank-18.0.1.0.0.2.dist-info/RECORD
